[
    {
        "title": "Learn Node in one day v.01",
        "author": "Diego Banovaz",
        "year": 2023
    },
    {
        "title": "Learn Node in one day v.01",
        "author": "Diego Banovaz",
        "year": 2023
    },
    {
        "title": "Learn Node in one day v.01",
        "author": "Diego Banovaz",
        "year": 2023
    },
    {
        "title": "Learn Node in one day v.01",
        "author": "Diego Banovaz",
        "year": 2023
    },
    {
        "title": "Learn Node in one day v.01",
        "author": "Diego Banovaz",
        "year": 2023
    },
    {
        "title": "Learn Node in one day v.01",
        "author": "Diego Banovaz",
        "year": 2023
    }
]